[
  {
    "isNew": false,
    "profileName": "PPLEXE5000TT001",
    "publishMode": "TcHmi",
    "targetDirectory": "",
    "server": "",
    "sitePath": "",
    "destinationUrl": "",
    "passiveMode": true,
    "savePassword": true,
    "deleteAllFilesBeforePublish": false,
    "deleteExtensionDataBeforePublish": false,
    "abortOnErrors": true,
    "userName": "",
    "encryptedPassword": "",
    "tcHmiServerHost": "10.0.0.11",
    "tcHmiServerPort": "1020",
    "socketTimeout": "5",
    "clientCertificateCN": "",
    "tcHmiUseTLS": true,
    "useClientCertificate": false,
    "tcHmiServerUserName": "__SystemAdministrator",
    "encryptedTcHmiServerPassword": "UQ8Ur+7n0M1GnNrnsUVhTw==",
    "tcHmiDestinationUrl": "https://10.0.0.11:1020",
    "publishConfiguration": "remote",
    "tcHmiSavePassword": true,
    "tcHmiIgnoreCertificateErrors": true
  },
  {
    "isNew": false,
    "profileName": "Test Platform",
    "publishMode": "TcHmi",
    "targetDirectory": "",
    "server": "",
    "sitePath": "",
    "destinationUrl": "",
    "passiveMode": true,
    "savePassword": true,
    "deleteAllFilesBeforePublish": false,
    "deleteExtensionDataBeforePublish": false,
    "abortOnErrors": true,
    "userName": "",
    "encryptedPassword": "",
    "tcHmiServerHost": "10.0.0.4",
    "tcHmiServerPort": "1020",
    "socketTimeout": "10",
    "clientCertificateCN": "",
    "tcHmiUseTLS": true,
    "useClientCertificate": false,
    "tcHmiServerUserName": "__SystemAdministrator",
    "encryptedTcHmiServerPassword": "060jyQ4lkX/EvYHb4tozaA==",
    "tcHmiDestinationUrl": "https://10.0.0.4:1020",
    "publishConfiguration": "remote",
    "tcHmiSavePassword": true,
    "tcHmiIgnoreCertificateErrors": true
  },
  {
    "isNew": false,
    "profileName": "Local",
    "publishMode": "TcHmi",
    "targetDirectory": "",
    "server": "",
    "sitePath": "",
    "destinationUrl": "",
    "passiveMode": true,
    "savePassword": true,
    "deleteAllFilesBeforePublish": false,
    "deleteExtensionDataBeforePublish": false,
    "abortOnErrors": true,
    "userName": "",
    "encryptedPassword": "",
    "tcHmiServerHost": "localhost",
    "tcHmiServerPort": "1010",
    "socketTimeout": "45",
    "clientCertificateCN": "",
    "tcHmiUseTLS": false,
    "useClientCertificate": false,
    "tcHmiServerUserName": "__SystemAdministrator",
    "encryptedTcHmiServerPassword": "WovSTREs1tlhiVIQmz0PXQ==",
    "tcHmiDestinationUrl": "http://localhost:1010",
    "publishConfiguration": "remote",
    "tcHmiSavePassword": true,
    "tcHmiIgnoreCertificateErrors": true
  }
]